hypergolic/__init__.py
hypergolic/agent_runner.py
hypergolic/analytics.py
hypergolic/app.py
hypergolic/config.py
hypergolic/conversation_manager.py
hypergolic/entrypoint.py
hypergolic/exploration.py
hypergolic/lifespan.py
hypergolic/migrate_sessions.py
hypergolic/pricing.py
hypergolic/providers.py
hypergolic/session_context.py
hypergolic/session_db.py
hypergolic/session_history.py
hypergolic/session_schema.py
hypergolic/session_stats.py
hypergolic/summarization.py
hypergolic/version_control.py
hypergolic/agents/__init__.py
hypergolic/agents/code_reviewer.py
hypergolic/agents/interrupts.py
hypergolic/agents/roles.py
hypergolic/agents/sub_agent.py
hypergolic/agents/trace.py
hypergolic/prompts/code_reviewer_system_prompt.md
hypergolic/prompts/paths.py
hypergolic/prompts/resolvers.py
hypergolic/prompts/summarize_context.md
hypergolic/prompts/system_prompt.md
hypergolic/tools/__init__.py
hypergolic/tools/approval_manager.py
hypergolic/tools/browser.py
hypergolic/tools/cancellation.py
hypergolic/tools/command_line.py
hypergolic/tools/common.py
hypergolic/tools/enums.py
hypergolic/tools/file_explorer.py
hypergolic/tools/file_operations.py
hypergolic/tools/git.py
hypergolic/tools/lsp.py
hypergolic/tools/merge_branch.py
hypergolic/tools/read_file.py
hypergolic/tools/schemas.py
hypergolic/tools/screenshot.py
hypergolic/tools/search_files.py
hypergolic/tools/tool_calls.py
hypergolic/tools/tool_list.py
hypergolic/tools/window_management.py
hypergolic/tools/code_review/__init__.py
hypergolic/tools/code_review/schemas.py
hypergolic/tui/__init__.py
hypergolic/tui/app.py
hypergolic/tui/callbacks.py
hypergolic/tui/session_tab.py
hypergolic/tui/sidebar_observer.py
hypergolic/tui/streaming.py
hypergolic/tui/styles.tcss
hypergolic/tui/tool_executor.py
hypergolic/tui/tool_ui_handler.py
hypergolic/tui/widgets/__init__.py
hypergolic/tui/widgets/clear_confirmation.py
hypergolic/tui/widgets/close_tab_confirmation.py
hypergolic/tui/widgets/conversation.py
hypergolic/tui/widgets/diff_view.py
hypergolic-0.7.0.dist-info/licenses/LICENSE
hypergolic-0.7.0.dist-info/METADATA
hypergolic-0.7.0.dist-info/WHEEL
hypergolic-0.7.0.dist-info/entry_points.txt
hypergolic-0.7.0.dist-info/top_level.txt
hypergolic-0.7.0.dist-info/RECORD
