Metadata-Version: 2.4
Name: hypergolic
Version: 0.7.0
Summary: Add your description here
Requires-Python: ==3.14.2
License-File: LICENSE
Requires-Dist: anthropic==0.76.0
Requires-Dist: jinja2>=3.1.6
Requires-Dist: pydantic>=2.12.5
Requires-Dist: pyobjc-framework-applicationservices>=12.1
Requires-Dist: pyobjc-framework-quartz>=12.1
Requires-Dist: pyyaml>=6.0
Requires-Dist: requests>=2.32.5
Requires-Dist: textual>=7.3.0
Requires-Dist: tiktoken>=0.12.0
Requires-Dist: ty>=0.0.12
Requires-Dist: typer>=0.21.1
Requires-Dist: playwright>=1.52.0
Dynamic: license-file
